teflo_terraform_plugin/__init__.py
teflo_terraform_plugin/teflo_terraform_plugin.py
teflo_terraform_plugin/files/schema.yml
teflo_terraform_plugin/files/schema_extensions.py
teflo_terraform_plugin/terraform_cli/terraform
teflo_terraform_plugin/terraform_helper/__init__.py
teflo_terraform_plugin/terraform_helper/helper.py
teflo_terraform_plugin-1.0.1.dist-info/AUTHORS
teflo_terraform_plugin-1.0.1.dist-info/LICENSE
teflo_terraform_plugin-1.0.1.dist-info/METADATA
teflo_terraform_plugin-1.0.1.dist-info/WHEEL
teflo_terraform_plugin-1.0.1.dist-info/entry_points.txt
teflo_terraform_plugin-1.0.1.dist-info/top_level.txt
teflo_terraform_plugin-1.0.1.dist-info/RECORD
