Metadata-Version: 2.1
Name: teflo-terraform-plugin
Version: 1.0.1
Summary: teflo provisioner plugin
Author: Red Hat Inc
License-File: LICENSE
License-File: AUTHORS
Requires-Dist: teflo
